fastapi_msal_patched/__init__.py
fastapi_msal_patched/auth.py
fastapi_msal_patched/py.typed
fastapi_msal_patched/clients/__init__.py
fastapi_msal_patched/clients/async_conf_client.py
fastapi_msal_patched/core/__init__.py
fastapi_msal_patched/core/msal_client_config.py
fastapi_msal_patched/core/session_manager.py
fastapi_msal_patched/core/utils.py
fastapi_msal_patched/models/__init__.py
fastapi_msal_patched/models/auth_code.py
fastapi_msal_patched/models/auth_token.py
fastapi_msal_patched/models/base_auth_model.py
fastapi_msal_patched/models/common.py
fastapi_msal_patched/models/id_token_claims.py
fastapi_msal_patched/models/local_account.py
fastapi_msal_patched/models/user_info.py
fastapi_msal_patched/security/__init__.py
fastapi_msal_patched/security/msal_auth_code_handler.py
fastapi_msal_patched/security/msal_scheme.py
fastapi_msal_patched-0.2.1.dist-info/LICENSE
fastapi_msal_patched-0.2.1.dist-info/WHEEL
fastapi_msal_patched-0.2.1.dist-info/METADATA
fastapi_msal_patched-0.2.1.dist-info/RECORD
