Metadata-Version: 2.1
Name: fastapi_msal_patched
Version: 0.2.1
Summary: FastAPI/MSAL - The MSAL (Microsoft Authentication Library) plugin for FastAPI!
Home-page: https://github.com/yaokaibb/fastapi_msal
Author: yaokai.fu
Author-email: yaokai.fu@bota.bio
Requires-Python: >=3.9
Classifier: Development Status :: 4 - Beta
Classifier: Intended Audience :: Developers
Classifier: Intended Audience :: Information Technology
Classifier: Intended Audience :: System Administrators
Classifier: Topic :: Software Development :: Libraries :: Python Modules
Classifier: Topic :: Software Development :: Libraries
Classifier: Topic :: Software Development
Classifier: Typing :: Typed
Classifier: Framework :: AsyncIO
Classifier: License :: OSI Approved :: MIT License
Classifier: Programming Language :: Python :: 3.9
Requires-Dist: pydantic
Requires-Dist: starlette
Requires-Dist: fastapi
Requires-Dist: msal
Requires-Dist: pydantic-settings==2.0.3
Requires-Dist: black ; extra == "dev"
Requires-Dist: pylint ; extra == "dev"
Requires-Dist: mypy ; extra == "dev"
Requires-Dist: python-multipart ; extra == "full"
Requires-Dist: itsdangerous ; extra == "full"
Provides-Extra: dev
Provides-Extra: full
